sandbox_evaluator_lib/__init__.py
sandbox_evaluator_lib/problem.py
sandbox_evaluator_lib/sandbox_evaluator.py
python_sandboxed_evaluator-0.1.0.dist-info/LICENSE
python_sandboxed_evaluator-0.1.0.dist-info/METADATA
python_sandboxed_evaluator-0.1.0.dist-info/WHEEL
python_sandboxed_evaluator-0.1.0.dist-info/top_level.txt
python_sandboxed_evaluator-0.1.0.dist-info/RECORD
