Metadata-Version: 2.2
Name: python-sandboxed-evaluator
Version: 0.1.0
Summary: A Python library for securely evaluating Python code in a sandboxed environment.
Home-page: https://github.com/iam-mhaseeb/Python-Sandboxed-Evaluator
Author: Muhammad Haseeb
Author-email: mhaseeb.inbox@gmail.com
Classifier: Programming Language :: Python :: 3
Classifier: License :: OSI Approved :: MIT License
Classifier: Operating System :: OS Independent
Requires-Python: >=3.6
License-File: LICENSE
Requires-Dist: RestrictedPython
Dynamic: author
Dynamic: author-email
Dynamic: classifier
Dynamic: description
Dynamic: description-content-type
Dynamic: home-page
Dynamic: requires-dist
Dynamic: requires-python
Dynamic: summary
